brp/__init__.py
brp-0.0.6.dist-info/LICENSE
brp-0.0.6.dist-info/METADATA
brp-0.0.6.dist-info/WHEEL
brp-0.0.6.dist-info/entry_points.txt
brp-0.0.6.dist-info/top_level.txt
brp-0.0.6.dist-info/RECORD
