Metadata-Version: 2.1
Name: brp
Version: 0.0.6
Summary: convert burpsuite export to python-requests
Author-email: Roberto Castellotti <me@rcastellotti.dev>
License: MIT License
Project-URL: Homepage, https://github.com/rcastellotti/brp
Keywords: feed,reader,tutorial
Classifier: License :: OSI Approved :: MIT License
Classifier: Programming Language :: Python
Classifier: Programming Language :: Python :: 3
Requires-Python: >=3.9
License-File: LICENSE
Requires-Dist: feedparser (>=5.2.0)
Requires-Dist: html2text
Requires-Dist: tomli ; python_version < "3.11"
